lotask/__init__.py
lotask/context.py
lotask/display.py
lotask/task.py
lotask-0.1.0.dist-info/WHEEL
lotask-0.1.0.dist-info/METADATA
lotask-0.1.0.dist-info/RECORD
