Metadata-Version: 2.1
Name: lotask
Version: 0.1.0
Summary: 
Author: dong
Author-email: ddliuhb@gmail.com
Requires-Python: >=3.8,<4.0
Classifier: Programming Language :: Python :: 3
Classifier: Programming Language :: Python :: 3.10
Classifier: Programming Language :: Python :: 3.8
Classifier: Programming Language :: Python :: 3.9
Requires-Dist: markdown2 (>=2.4.2,<3.0.0)
